hubblenetwork/__init__.py
hubblenetwork/ble.py
hubblenetwork/cli.py
hubblenetwork/cloud.py
hubblenetwork/crypto.py
hubblenetwork/device.py
hubblenetwork/errors.py
hubblenetwork/org.py
hubblenetwork/packets.py
hubblenetwork/ready.py
pyhubblenetwork-0.1.0.dist-info/METADATA
pyhubblenetwork-0.1.0.dist-info/WHEEL
pyhubblenetwork-0.1.0.dist-info/entry_points.txt
pyhubblenetwork-0.1.0.dist-info/licenses/LICENSE
pyhubblenetwork-0.1.0.dist-info/RECORD
