Metadata-Version: 2.4
Name: pyhubblenetwork
Version: 0.1.0
Summary: Hubble SDK host-side tools
Author-email: Paul Buckley <paul@hubble.com>
License-Expression: Apache-2.0
License-File: LICENSE
Classifier: Operating System :: OS Independent
Classifier: Programming Language :: Python :: 3
Requires-Python: >=3.9
Requires-Dist: bleak
Requires-Dist: click
Requires-Dist: httpx>=0.27
Requires-Dist: pycryptodome
Requires-Dist: questionary>=2.0.0
Requires-Dist: tabulate>=0.9.0
Provides-Extra: dev
Requires-Dist: mypy; extra == 'dev'
Requires-Dist: pytest-cov; extra == 'dev'
Requires-Dist: pytest>=7; extra == 'dev'
Requires-Dist: ruff; extra == 'dev'
